Metadata-Version: 1.1
Name: microservices
Version: 0.31.0
Summary: Microservices builder
Home-page: https://github.com/viatoriche/microservices
Author: viatoriche
Author-email: maxim@via-net.org
License: MIT
Download-URL: https://github.com/viatoriche/microservices/tarball/0.31.0
Platform: UNKNOWN
